{
  "main_category": "lifestyle",
  "sub_category": "Travel",
  "courses": [
    {
      "title": "How to Move, Live, and Work Abroad: Start Your Expat Journey",
      "url": "https://www.udemy.com/course/how-to-move-live-and-work-abroad-start-your-expat-journey/"
    },
    {
      "title": "How to Move, Live, and Work Abroad: Settling Into Expat Life",
      "url": "https://www.udemy.com/course/how-to-move-live-and-work-abroad-settling-into-expat-life/"
    },
    {
      "title": "Molla tutto e trasferisciti all'estero",
      "url": "https://www.udemy.com/course/crea-la-vita-dei-tuoi-sogni-disegna-pianifica/"
    },
    {
      "title": "Cleverer Reisen - Travel Smart",
      "url": "https://www.udemy.com/course/how-to-travel-smart/"
    },
    {
      "title": "Travel Hacking and Credit Card Reward Basics!",
      "url": "https://www.udemy.com/course/travel-hacking-earn-free-flights-around-the-world/"
    },
    {
      "title": "10 Segredos para Economizar com Hotéis durante sua Viagem",
      "url": "https://www.udemy.com/course/segredos-economizar-hospedagem-viagem/"
    },
    {
      "title": "Weltreise als Sparmaßnahme",
      "url": "https://www.udemy.com/course/weltreise-als-sparmanahme/"
    },
    {
      "title": "How to Find the Cheapest Flights with Google Flights",
      "url": "https://www.udemy.com/course/how-to-find-the-cheapest-flights-google-flights/"
    },
    {
      "title": "Montenegro Travel Guide",
      "url": "https://www.udemy.com/course/montenegrotravelguide/"
    },
    {
      "title": "Women's Travel Safety Secrets: Learn to STAY SAFE traveling!",
      "url": "https://www.udemy.com/course/travel-safety-for-women/"
    },
    {
      "title": "Almanya'da Hayat",
      "url": "https://www.udemy.com/course/almanyadahayat/"
    },
    {
      "title": "Become a Digital Nomad: Master the Travel Lifestyle",
      "url": "https://www.udemy.com/course/digital-nomad-guide/"
    },
    {
      "title": "Travel like a Pro: for all aspiring travellers",
      "url": "https://www.udemy.com/course/travelwithjules/"
    },
    {
      "title": "Prepare for your first trip to Africa",
      "url": "https://www.udemy.com/course/prepare-for-your-first-trip-to-africa/"
    },
    {
      "title": "EFT Your Travel Stress and Fear of Flying",
      "url": "https://www.udemy.com/course/eft-for-travel-and-fearful-flyers/"
    },
    {
      "title": "Usare AGENDE VISIVE e TASK ANALYSIS con bambini autistici",
      "url": "https://www.udemy.com/course/agendavisiva_taskanalysis/"
    },
    {
      "title": "How to Immigrate to Portugal",
      "url": "https://www.udemy.com/course/moving-to-portugal/"
    },
    {
      "title": "世界を旅した経営者が語る人生が変わる“カナダ移住”のリアル",
      "url": "https://www.udemy.com/course/rnidrbmw/"
    },
    {
      "title": "Jakobsweg Komplettkurs - die perfekte Vorbereitung",
      "url": "https://www.udemy.com/course/jakobsweg-komplettkurs-die-perfekte-vorbereitung/"
    },
    {
      "title": "SEGMENTATION IN THE TRAVEL BUSINESS",
      "url": "https://www.udemy.com/course/segmentation-in-the-travel-business/"
    },
    {
      "title": "Travel Hacking Hotels: Get Upgrades, Free Trips, and More",
      "url": "https://www.udemy.com/course/travel-revolution-travel-hacking-hotels/"
    },
    {
      "title": "Mini Maui Travel Guide",
      "url": "https://www.udemy.com/course/mini-maui-travel-guide-i/"
    },
    {
      "title": "Switzerland - The FREE Course",
      "url": "https://www.udemy.com/course/switzerland-the-free-course/"
    },
    {
      "title": "NAVIGATION: Piloting Small Boats",
      "url": "https://www.udemy.com/course/navigation_piloting-small-boats/"
    },
    {
      "title": "How Some Hikers Almost Always Know Their Way in the Wild.",
      "url": "https://www.udemy.com/course/wilderness-navigation-masters/"
    },
    {
      "title": "Turismo Responsável: Como ser um Turista Melhor",
      "url": "https://www.udemy.com/course/turismo-responsavel/"
    },
    {
      "title": "How to Trek Manaslu Mountains in Nepal",
      "url": "https://www.udemy.com/course/trekmanaslu/"
    },
    {
      "title": "Como fazer intercâmbio para estudar fora sem gastar muito.",
      "url": "https://www.udemy.com/course/como-fazer-intercambio-para-estudar-fora-sem-gastar-muito/"
    },
    {
      "title": "How to Move Abroad as a Skilled Professional: Work Abroad",
      "url": "https://www.udemy.com/course/how-to-move-abroad-as-a-skilled-professional/"
    },
    {
      "title": "A'dan Z'ye Interrail Rehberi",
      "url": "https://www.udemy.com/course/interrail/"
    },
    {
      "title": "How to Move Abroad: Immigration as an Expat Abroad A to Z",
      "url": "https://www.udemy.com/course/moving-abroad-everything-you-need-to-know-before-moving/"
    },
    {
      "title": "Retreat Training: Rock Your Profitable, Sold-Out Retreats",
      "url": "https://www.udemy.com/course/retreat-training/"
    },
    {
      "title": "Flight Hacking - How To Find Cheap Flights",
      "url": "https://www.udemy.com/course/flight-hacking-how-to-find-cheap-flights/"
    },
    {
      "title": "Vivere all'Estero con Successo!",
      "url": "https://www.udemy.com/course/vivere-allestero-con-successo/"
    },
    {
      "title": "ADV-101 An Introduction to Adventure Motorcycle Riding",
      "url": "https://www.udemy.com/course/adv-101-an-introduction-to-adventure-motorcycle-riding/"
    },
    {
      "title": "How to Get Visa and travel to any country you like.",
      "url": "https://www.udemy.com/course/how-to-get-visa-and-travel-to-any-country-you-like/"
    },
    {
      "title": "The Ultimate Guide to Travel Budgeting",
      "url": "https://www.udemy.com/course/the-ultimate-guide-to-travel-budgeting/"
    },
    {
      "title": "The Ultimate Budget-Friendly Europe Travel Guide",
      "url": "https://www.udemy.com/course/the-ultimate-budget-friendly-europe-travel-guide/"
    },
    {
      "title": "Travel Hacking: A Backpacker Exposes How To Travel for Free",
      "url": "https://www.udemy.com/course/freetravel/"
    },
    {
      "title": "10 minutes to know Beijing",
      "url": "https://www.udemy.com/course/overview-beijing/"
    },
    {
      "title": "Mastering COLREGs | Marine navigation rules",
      "url": "https://www.udemy.com/course/mastering-colregs-marine-navigation-rules/"
    },
    {
      "title": "An Intimate Look into Thai Culture",
      "url": "https://www.udemy.com/course/thai-culture/"
    },
    {
      "title": "Hooray for the Holidays!",
      "url": "https://www.udemy.com/course/hooray-holidays/"
    },
    {
      "title": "Social Media Marketing : Hospitality & Travel Professionals",
      "url": "https://www.udemy.com/course/social-media-marketing-for-hospitality-industry/"
    },
    {
      "title": "Travel & Tourism Management",
      "url": "https://www.udemy.com/course/skylark-travel-tourism-management/"
    },
    {
      "title": "Língua dinamarquesa \"do zero\" (em portugués)",
      "url": "https://www.udemy.com/course/lingua-dinamarquesa-do-zero/"
    },
    {
      "title": "経験者が語る、カナダ起業ビザ移住スキーム徹底解体",
      "url": "https://www.udemy.com/course/xagcwfvv/"
    },
    {
      "title": "How To Be Totally Free & Paperless & Digital in 2 Weeks!",
      "url": "https://www.udemy.com/course/master-a-super-simple-life-going-totally-paperlessdigital/"
    },
    {
      "title": "How to Travel the World on Any Budget - A Complete Guide",
      "url": "https://www.udemy.com/course/how-to-travel-the-world-on-any-budget/"
    },
    {
      "title": "Private Pilot Ground School",
      "url": "https://www.udemy.com/course/pplground/"
    },
    {
      "title": "Learn to use famous Chinese apps",
      "url": "https://www.udemy.com/course/learn-to-use-famous-chinese-apps/"
    },
    {
      "title": "Curso de Viagens, Couchsurfing e Voluntariado",
      "url": "https://www.udemy.com/course/viagens-couchsurfing-voluntariado/"
    },
    {
      "title": "Como Planejar uma Viagem do Zero | Crie seu Próprio Roteiro",
      "url": "https://www.udemy.com/course/como-planejar-uma-viagem-roteiro/"
    },
    {
      "title": "How to Be a Digital Nomad - Achieve Location Independence",
      "url": "https://www.udemy.com/course/how-to-be-a-digital-nomad-travel-hacks/"
    },
    {
      "title": "Land Transportation Office (LTO) Exam Reviewer (Philippines)",
      "url": "https://www.udemy.com/course/land-transportation-office-lto-exam-reviewer-philippines/"
    },
    {
      "title": "How to set up life in Los Angeles in 30 days",
      "url": "https://www.udemy.com/course/90-days-in-la-step-by-step-for-setting-up-your-new-life/"
    },
    {
      "title": "Existence of Soul",
      "url": "https://www.udemy.com/course/shah-yaqeeq-baba/"
    },
    {
      "title": "How To Travel on a Budget",
      "url": "https://www.udemy.com/course/how-to-travel-on-a-budget/"
    },
    {
      "title": "Northern Lights - The Ultimate Guide (2023)",
      "url": "https://www.udemy.com/course/northern-lights/"
    },
    {
      "title": "How to DIY Australian Partner Visa Without a Lawyer",
      "url": "https://www.udemy.com/course/how-to-diy-australian-partner-visa-without-a-lawyer/"
    },
    {
      "title": "How to Travel the World",
      "url": "https://www.udemy.com/course/how-to-travel-the-world-z/"
    },
    {
      "title": "Airbnb Made Simple: Make Easy Residual Income This Year",
      "url": "https://www.udemy.com/course/how-to-make-money-on-airbnb/"
    },
    {
      "title": "Female World Traveler 101",
      "url": "https://www.udemy.com/course/femaleworldtraveler/"
    },
    {
      "title": "Travel Writing and Blogging Masterclass - CPD Accredited",
      "url": "https://www.udemy.com/course/travel-writing/"
    },
    {
      "title": "AVOID Travel Scams & Scammers Complete Course: Travel Safety",
      "url": "https://www.udemy.com/course/travel-scams-master-class/"
    },
    {
      "title": "Viaje Mais Gastando Menos: Milhas, Voos e Hospedagem",
      "url": "https://www.udemy.com/course/seja-um-viajante-independente-3-cursos-pelo-preco-de-1/"
    },
    {
      "title": "The Ultimate Guide to Become a World Traveler – Expert Tips!",
      "url": "https://www.udemy.com/course/travel-cheap/"
    },
    {
      "title": "(Free Course) New Normal Abroad",
      "url": "https://www.udemy.com/course/free-course-new-normal-abroad/"
    },
    {
      "title": "Denver Travel Guide",
      "url": "https://www.udemy.com/course/denvertravelguide/"
    },
    {
      "title": "Explore Waterton National Park Before You Go",
      "url": "https://www.udemy.com/course/watertonnationalparkwiththetwocowboys/"
    },
    {
      "title": "Freedom to Travel: Learn to Live the Digital Nomad Lifestyle",
      "url": "https://www.udemy.com/course/freedom-to-travel/"
    },
    {
      "title": "India Exploration & Adventure, Travel Tribe Culture Series",
      "url": "https://www.udemy.com/course/travel-tribe-india/"
    },
    {
      "title": "Become a Successful International House Sitter",
      "url": "https://www.udemy.com/course/house-sitting/"
    },
    {
      "title": "How to Host One Room on Airbnb for Extra Income",
      "url": "https://www.udemy.com/course/roomhosting101/"
    },
    {
      "title": "World's Greatest Travel Bargains",
      "url": "https://www.udemy.com/course/world-greatest-travel-bargains/"
    },
    {
      "title": "Исландский язык \"с нуля\"",
      "url": "https://www.udemy.com/course/icelandic-new/"
    },
    {
      "title": "DIGITAL NOMAD MASTERY - How to Travel The World for Free",
      "url": "https://www.udemy.com/course/digital-nomads-world-travel/"
    },
    {
      "title": "A Beginner's Guide to International Travel Planning",
      "url": "https://www.udemy.com/course/international-travel-planning/"
    },
    {
      "title": "WATCH YOUR TRAVEL BUSINESS TAKE FLIGHT",
      "url": "https://www.udemy.com/course/watch-your-travel-business-take-flight/"
    },
    {
      "title": "Astuces voyage: Voyager LIBREMENT sans se ruiner",
      "url": "https://www.udemy.com/course/astuces-voyage-voyager-sans-se-ruiner/"
    },
    {
      "title": "Die besten Travel-Hacks",
      "url": "https://www.udemy.com/course/die-besten-travel-hacks/"
    },
    {
      "title": "海外移住・海外就職完全マニュアル",
      "url": "https://www.udemy.com/course/working_abroad/"
    },
    {
      "title": "Canada Immigration - The Ultimate Step-by-Step Guide",
      "url": "https://www.udemy.com/course/canada-immigration-the-ultimate-step-by-step-guide/"
    },
    {
      "title": "Aprenda A Viajar Barato Pelo Mundo - Versão Pós Pandemia",
      "url": "https://www.udemy.com/course/curso-completo-aprenda-a-viajar-barato-pelo-mundo/"
    },
    {
      "title": "Buy cheap plane tickets for 10% of their initial price.",
      "url": "https://www.udemy.com/course/buy-cheap-plane-tickets-for-10-of-their-initial-price/"
    },
    {
      "title": "How to Travel Around the World on a Budget in 2023",
      "url": "https://www.udemy.com/course/how-to-travel-around-the-world-on-a-budget/"
    },
    {
      "title": "How to use Travel Design to create perfect travel adventures",
      "url": "https://www.udemy.com/course/travel-design/"
    },
    {
      "title": "Create a 1st Class Nanny CV with The Hotel Nanny",
      "url": "https://www.udemy.com/course/create-a-1st-class-nanny-cv-with-the-hotel-nanny/"
    },
    {
      "title": "Insider Travel to Italy (including Italian Lessons)",
      "url": "https://www.udemy.com/course/travel-to-italy/"
    },
    {
      "title": "Como Encontrar Voos Mais Baratos no Google Flights na Viagem",
      "url": "https://www.udemy.com/course/como-encontrar-voos-mais-baratos-no-google-flights/"
    },
    {
      "title": "BLOG MASTERY - How to Make, Market, and Monetize your Blog",
      "url": "https://www.udemy.com/course/digital-nomad-travel-blogging/"
    },
    {
      "title": "Yeni başlayanlar için Danca dili (Türkçe)",
      "url": "https://www.udemy.com/course/yeni-baslayanlar-icin-danca-dili/"
    },
    {
      "title": "High Altitude Vacationing",
      "url": "https://www.udemy.com/course/high-altitude-vacationing/"
    },
    {
      "title": "The Ultimate Camino de Santiago Preparation Course",
      "url": "https://www.udemy.com/course/camino-de-santiago-prep-course/"
    },
    {
      "title": "Immigrate to the USA as an International Physician",
      "url": "https://www.udemy.com/course/immigrate-to-the-usa-as-an-international-physician/"
    },
    {
      "title": "How To Walk The Camino de Santiago",
      "url": "https://www.udemy.com/course/how-to-walk-the-camino-de-santiago/"
    },
    {
      "title": "How to study abroad in the US and English-speaking countries",
      "url": "https://www.udemy.com/course/how-to-study-abroad-in-the-us/"
    },
    {
      "title": "Juneau Travel Guide",
      "url": "https://www.udemy.com/course/juneautravelguide/"
    },
    {
      "title": "How to Visit or Move to Africa: A Step-by-Step Success Plan",
      "url": "https://www.udemy.com/course/visit-move-to-africa-course/"
    },
    {
      "title": "HOWEXPERT VIDEO BOOK - Mini Maui Travel Guide",
      "url": "https://www.udemy.com/course/mini-maui-travel-guide/"
    },
    {
      "title": "Honeymoon Secrets",
      "url": "https://www.udemy.com/course/honeymoon-secrets/"
    },
    {
      "title": "How to Choose the Right Day Hiking Gear",
      "url": "https://www.udemy.com/course/day-hiking-gear/"
    },
    {
      "title": "How To Start A Travel Blog in 1 Hour - FREE Guide Included",
      "url": "https://www.udemy.com/course/start-a-travel-blog/"
    },
    {
      "title": "Словенский язык для начинающих: 30 уроков по грамматике",
      "url": "https://www.udemy.com/course/znam-slovensko/"
    },
    {
      "title": "How to be a Tour Guide in your Hometown Overnight",
      "url": "https://www.udemy.com/course/how-to-be-a-tour-guide/"
    },
    {
      "title": "How to Move Abroad to Escape Trump’s America",
      "url": "https://www.udemy.com/course/ditch-america/"
    },
    {
      "title": "Essential Japanese Etiquette, Phrases & Tips for Travelers",
      "url": "https://www.udemy.com/course/japanese-etiquette-practical-phrases-travel-tips/"
    },
    {
      "title": "ADV-102 Everything to know for Adventure Motorcycle Riding",
      "url": "https://www.udemy.com/course/adv-102-everything-to-know-for-adventure-motorcycle-riding/"
    },
    {
      "title": "Comment Réussir l'Entrée Express Canada sans se Ruiner-2024",
      "url": "https://www.udemy.com/course/comment-reussir-lentree-express-canada-sans-se-ruiner-2022/"
    },
    {
      "title": "How African Americans can Relocate to Africa",
      "url": "https://www.udemy.com/course/how-african-americans-can-relocate-to-africa/"
    },
    {
      "title": "Your Guide To Traveling On An Amazing Overseas Vacation.",
      "url": "https://www.udemy.com/course/how-to-travel-on-an-overseas-vacation/"
    },
    {
      "title": "Travel Hacking Basics - How To Travel Longer & Better!",
      "url": "https://www.udemy.com/course/travel-hacking-basics-how-to-travel-longer-better/"
    },
    {
      "title": "Paris 2.0",
      "url": "https://www.udemy.com/course/paris-20/"
    },
    {
      "title": "19 Year Old World Traveler",
      "url": "https://www.udemy.com/course/19-year-old-world-traveler/"
    },
    {
      "title": "USA Immigration: Skilled Immigrant Visas + Investment Visas",
      "url": "https://www.udemy.com/course/usa-immigration-skilled-immigrant-visas-investment-visas/"
    },
    {
      "title": "International Au Pair (nanny) Working in the USA Handbook",
      "url": "https://www.udemy.com/course/international-au-pair-nanny-working-in-the-usa-handbook/"
    },
    {
      "title": "Retire in Latin America for Seniors",
      "url": "https://www.udemy.com/course/retire-in-latin-america-for-seniors/"
    },
    {
      "title": "Travel Writing: Explore the World & Publish Your Stories!",
      "url": "https://www.udemy.com/course/travel-writing-class/"
    },
    {
      "title": "Deep Travel: Have Adventures No Guidebook Can Tell You About",
      "url": "https://www.udemy.com/course/deep-travel-with-dave-fox/"
    },
    {
      "title": "Come viaggiare gratis (o quasi) nel 2025",
      "url": "https://www.udemy.com/course/viaggiare-gratis-2025/"
    },
    {
      "title": "Agente de Viajes Profesional",
      "url": "https://www.udemy.com/course/agente-de-viajes-profesional/"
    },
    {
      "title": "Gardaland - 100 cose da sapere prima di una gita al Parco",
      "url": "https://www.udemy.com/course/gardaland/"
    },
    {
      "title": "Macetes e Dicas para Economizar até 49% em Viagens",
      "url": "https://www.udemy.com/course/macetes-e-dicas-para-economizar-ate-49-em-viagens/"
    },
    {
      "title": "Walking Tour Guiding",
      "url": "https://www.udemy.com/course/walking-tour-guiding/"
    },
    {
      "title": "Elevate Travel: 7 Pillars for Thriving as a Productive Nomad",
      "url": "https://www.udemy.com/course/elevate-travel-7-pillars-for-thriving-as-a-productive-nomad/"
    },
    {
      "title": "Transform Your Travel Writing Adventure into Words that Sell",
      "url": "https://www.udemy.com/course/transform-your-travel-writing-adventure-into-words-that-sell/"
    },
    {
      "title": "AI-Powered Travel Writing: Master Manual Writing & Vlogging",
      "url": "https://www.udemy.com/course/ai-powered-travel-writing-master-manual-writing-vlogging/"
    },
    {
      "title": "Airplane Crosswind Landings",
      "url": "https://www.udemy.com/course/crosswind-landings/"
    },
    {
      "title": "How To Vlog & Create a Sustainable Passive Income",
      "url": "https://www.udemy.com/course/how-to-vlog-with-jord/"
    },
    {
      "title": "How To Become a Digital Nomad: The Ultimate Travel Hack",
      "url": "https://www.udemy.com/course/lifestyle-design-101-location-independence-world-travel/"
    },
    {
      "title": "Immigrate to the USA: All US Work Visas Guide",
      "url": "https://www.udemy.com/course/immigrate-to-the-usa-all-us-work-visas-guide/"
    },
    {
      "title": "Becoming a Travel Writer: Turn Wanderlust into a Career",
      "url": "https://www.udemy.com/course/travel-writing-writing-and-blogging-about-travel-for-money/"
    },
    {
      "title": "Basura Cero al Aire Libre",
      "url": "https://www.udemy.com/course/basura-cero-al-aire-libre/"
    },
    {
      "title": "Permis de Travail au Canada et Résidence Permanente en 1H",
      "url": "https://www.udemy.com/course/permis-de-travail-au-canada-et-residence-permanente-en-1h/"
    },
    {
      "title": "Learn Basic Nepali Language",
      "url": "https://www.udemy.com/course/learn-basic-nepali-language/"
    },
    {
      "title": "Travel Hacking: How to Travel the World for Next to Nothing",
      "url": "https://www.udemy.com/course/travel-hacking/"
    },
    {
      "title": "Become a V.I.P Nanny (Course Two)",
      "url": "https://www.udemy.com/course/become-a-vip-nanny-course-two/"
    },
    {
      "title": "Step by step guide to creating your Express Entry profile",
      "url": "https://www.udemy.com/course/step-by-step-guide-to-creating-your-express-entry-profile/"
    },
    {
      "title": "Plan Your Dream Solo Trip in 2025",
      "url": "https://www.udemy.com/course/plan-your-dream-solo-trip/"
    },
    {
      "title": "Become a V.I.P Nanny (Course One)",
      "url": "https://www.udemy.com/course/become-a-vip-nanny-course-one/"
    },
    {
      "title": "How to find the cheapest flights to any destination",
      "url": "https://www.udemy.com/course/how-to-find-the-cheapest-flights-to-any-destination/"
    },
    {
      "title": "Finanças para Viagem: Aprenda a Planejar sua Viagem do Zero",
      "url": "https://www.udemy.com/course/financas-dinheiro-planejar-viagem/"
    },
    {
      "title": "Travel Writing for Beginners: Story Structure and Craft",
      "url": "https://www.udemy.com/course/travel-writing-for-beginners/"
    },
    {
      "title": "The Complete Guide to Travel Hacking 2.0",
      "url": "https://www.udemy.com/course/the-complete-guide-to-travel-hacking-2/"
    },
    {
      "title": "Dark tourism:Exploring the Shadows.",
      "url": "https://www.udemy.com/course/dark-tourismexploring-the-shadows/"
    },
    {
      "title": "Cameriere di Successo, Corso Completo sul Servizio Sala",
      "url": "https://www.udemy.com/course/fb-luxury-standards/"
    },
    {
      "title": "Mini London Travel Guide",
      "url": "https://www.udemy.com/course/mini-london-travel-guide/"
    },
    {
      "title": "Solo World Traveler",
      "url": "https://www.udemy.com/course/solo-world-traveler/"
    },
    {
      "title": "How to apply a Schengen Visa and move to Europe?",
      "url": "https://www.udemy.com/course/how-to-obtain-a-schengen-visa-and-move-to-italy/"
    },
    {
      "title": "Egypt 101-Your Guide To Be A Local Egyptian",
      "url": "https://www.udemy.com/course/egypt101/"
    },
    {
      "title": "Video Travel Guide \"France Like a local\"",
      "url": "https://www.udemy.com/course/video-travel-guide-france-like-a-local/"
    },
    {
      "title": "Master Answering F1 Visa Interview Questions",
      "url": "https://www.udemy.com/course/master-answering-f1-visa-interview-questions/"
    },
    {
      "title": "Curso de Motociclismo",
      "url": "https://www.udemy.com/course/curso-de-motociclismo/"
    },
    {
      "title": "Relocate to the USA – Guide to Financial Planning",
      "url": "https://www.udemy.com/course/relocate-to-the-usa-guide-to-financial-planning/"
    },
    {
      "title": "How to Immigrate to Canada Using Express Entry",
      "url": "https://www.udemy.com/course/canadianexpressentry/"
    },
    {
      "title": "How to Travel Europe Cheap",
      "url": "https://www.udemy.com/course/how-to-travel-europe-cheap/"
    },
    {
      "title": "Immigration to the United States: Work Visa H-1B",
      "url": "https://www.udemy.com/course/immigration-to-the-united-states-work-visa-h-1b-visa/"
    },
    {
      "title": "East Asia, Ultimate Bucket List, Travel Tribe",
      "url": "https://www.udemy.com/course/ubl-traveltribe-eastasia/"
    },
    {
      "title": "パスポート不要！お金をかけずに自宅にいながらリアルな英語を習得し、国際的な人脈を築きながら世界中に無料宿泊所を作る方法",
      "url": "https://www.udemy.com/course/couchsufing/"
    },
    {
      "title": "Le guide pour devenir digital nomade",
      "url": "https://www.udemy.com/course/nomad-digital/"
    },
    {
      "title": "Travel Hacking for Free Flights: Finally See the World!",
      "url": "https://www.udemy.com/course/travelhacking/"
    },
    {
      "title": "20 Types/Ιdeas of Tourism. Α Complete Tourism Guide.",
      "url": "https://www.udemy.com/course/20-typesdeas-of-tourism-complete-tourism-guide/"
    },
    {
      "title": "INTERNATIONAL TOURISM",
      "url": "https://www.udemy.com/course/international-tourism-v/"
    },
    {
      "title": "Fly Guide to Brazil Webinar",
      "url": "https://www.udemy.com/course/flyguidetobrazil/"
    },
    {
      "title": "UK Visitor Visa Made Simple: A Step-by-Step Guide for First",
      "url": "https://www.udemy.com/course/uk-visitor-visa-made-simple-a-step-by-step-guide/"
    },
    {
      "title": "【有料級-カナダ永住ルート】どのビザが一番早く・安く永住権獲得可能!? カナダ移住にかかる時間と料金をビザ毎に徹底比較！",
      "url": "https://www.udemy.com/course/ezfkkeco/"
    },
    {
      "title": "[オーストラリア・ワーホリ準備完全攻略] これ一本で入国/仕事探し/シェアハウス/必須英語フレーズ全部解説！",
      "url": "https://www.udemy.com/course/australia-workingholiday/"
    },
    {
      "title": "Backcountry Camping For Beginners",
      "url": "https://www.udemy.com/course/backcountrycampingforbeginners/"
    },
    {
      "title": "信頼されるホストになるために：成功ホストに学ぶCouchsurfing実践講座【実録メッセージ付き】",
      "url": "https://www.udemy.com/course/couchsurfing_expert/"
    },
    {
      "title": "Travel Hacking Airlines: Fly For Free",
      "url": "https://www.udemy.com/course/travel-revolution/"
    },
    {
      "title": "De cero a viajero, el paso a paso para organizar viajes",
      "url": "https://www.udemy.com/course/deceroaviajeroporsofiaposse/"
    },
    {
      "title": "A Beginner's Guide To Becoming a Travel Director",
      "url": "https://www.udemy.com/course/a-beginners-guide-to-becoming-a-travel-director/"
    },
    {
      "title": "The Complete Guide to Travel Hacking",
      "url": "https://www.udemy.com/course/the-complete-guide-to-travel-hacking/"
    },
    {
      "title": "What You Need to Know About Tiny Living",
      "url": "https://www.udemy.com/course/what-you-need-to-know-about-tiny-living/"
    },
    {
      "title": "Camino de Santiago - Master Preparation Guide for the Camino",
      "url": "https://www.udemy.com/course/camino-de-santiago-ultimate-preparation-guide/"
    },
    {
      "title": "How to Make a Successful Move Abroad: Easy Transition Guide",
      "url": "https://www.udemy.com/course/how-to-make-a-successful-move-abroad-easy-transition-guide/"
    },
    {
      "title": "Credit Card Rewards 101: How to Earn Free Travel and More",
      "url": "https://www.udemy.com/course/credit-card-rewards-101-earn-free-cash-and-travel/"
    },
    {
      "title": "immigration to the USA: J-1 Visa, Comprehensive Guide",
      "url": "https://www.udemy.com/course/immigration-to-the-usa-j-1-visa-comprehensive-guide/"
    },
    {
      "title": "Adventure GPS Navigation: Build, Load & Use GPX",
      "url": "https://www.udemy.com/course/gps-mastery-for-adventurers/"
    },
    {
      "title": "Como trabalhar com ''Literatura de viagem''?",
      "url": "https://www.udemy.com/course/como-trabalhar-com-literatura-de-viagem/"
    },
    {
      "title": "كورس شامل عن تأشيرة شنجن وكيفية الحصول عليها",
      "url": "https://www.udemy.com/course/woqjaubb/"
    },
    {
      "title": "Moving to the USA as an International Nurse",
      "url": "https://www.udemy.com/course/moving-to-the-usa-as-an-international-nurse/"
    },
    {
      "title": "Travel Hacking: Explore The World for Less Than You Imagined",
      "url": "https://www.udemy.com/course/travel-hacking-explore-the-world-for-less-than-you-imagined/"
    },
    {
      "title": "Online Resources for Exploring Old Railways in the UK",
      "url": "https://www.udemy.com/course/online-resources-for-exploring-old-railways-in-the-uk/"
    },
    {
      "title": "【台湾一人旅】複雑な公共交通が要らない！台湾鉄道で充実した一人旅を実現し、帰国したくない！",
      "url": "https://www.udemy.com/course/nyktbewn/"
    },
    {
      "title": "Break Free from Your Timeshare: Learn from a Former Insider",
      "url": "https://www.udemy.com/course/the-complete-timeshare-cancellation-guide/"
    },
    {
      "title": "Japan Travel Tips & Etiquette for First-Time Visitors 2025",
      "url": "https://www.udemy.com/course/manabitomonijapanesetraveletiquetteandcommonsense/"
    },
    {
      "title": "Voyage à Vélo : Votre Guide Complet du Cyclotourisme !",
      "url": "https://www.udemy.com/course/le-guide-ultime-du-voyage-a-velo/"
    },
    {
      "title": "Come diventare un Travel Influencer",
      "url": "https://www.udemy.com/course/travel-influencer/"
    },
    {
      "title": "EV Master Class - English",
      "url": "https://www.udemy.com/course/ev-master-class-english/"
    },
    {
      "title": "Becoming an Expat (Moving & Living Abroad for Extrepreneurs)",
      "url": "https://www.udemy.com/course/how-to-move-and-live-abroad/"
    },
    {
      "title": "How To Have Fun At An Amusement Park",
      "url": "https://www.udemy.com/course/how-to-have-fun-at-an-amusement-park/"
    },
    {
      "title": "Your Guide to Life in the UK -For Foreigners",
      "url": "https://www.udemy.com/course/your-guide-to-life-in-the-uk-for-foreigners/"
    },
    {
      "title": "Ethics of travel",
      "url": "https://www.udemy.com/course/ethics-of-travel/"
    },
    {
      "title": "[마이크임팩트 청춘대학] 어서와, 혼자 여행은 처음이지?",
      "url": "https://www.udemy.com/course/youthcollege_namgeumkim/"
    },
    {
      "title": "跨文化適應：鳥瞰全貌",
      "url": "https://www.udemy.com/course/ccaintrocn/"
    },
    {
      "title": "A weekend in Warsaw",
      "url": "https://www.udemy.com/course/a-weekend-in-warsaw/"
    },
    {
      "title": "Winter Camping for Beginners",
      "url": "https://www.udemy.com/course/winter-camping-for-beginners/"
    },
    {
      "title": "Cheap Travel - Travel the World on 15 a day",
      "url": "https://www.udemy.com/course/cheap-travel-travel-the-world-on-15-a-day/"
    },
    {
      "title": "Learn how to snorkeling effectively",
      "url": "https://www.udemy.com/course/learn-how-to-snorkeling-effectively/"
    },
    {
      "title": "Tirar Visto Americano: Guia Completo DS160 para Brasileiros",
      "url": "https://www.udemy.com/course/tirar-visto-americano-guia-completo-ds160-para-brasileiros/"
    },
    {
      "title": "Wie du die perfekte Reise planst - am Beispiel von Japan",
      "url": "https://www.udemy.com/course/japan-reise-planen/"
    },
    {
      "title": "39 Travel Tips to Make Your Travel More Enjoyable - 1 Hour",
      "url": "https://www.udemy.com/course/39-travel-tips-to-make-your-travel-more-enjoyable-1-hour/"
    },
    {
      "title": "Mastering Airbnb | Learn from SF's top host, 100+ lectures",
      "url": "https://www.udemy.com/course/mastering-airbnb-learn-from-sfs-top-host/"
    },
    {
      "title": "Gérer son stress en mission humanitaire",
      "url": "https://www.udemy.com/course/gerer-son-stress-en-mission-humanitaire/"
    },
    {
      "title": "Travel Hacking Mastery: Travel Around the World for Cheap",
      "url": "https://www.udemy.com/course/travel-hacking-fly-anywhere-in-the-world-for-less-than-150/"
    },
    {
      "title": "Travel The World House Sitting - Get the Sits!",
      "url": "https://www.udemy.com/course/travel-the-world-house-sitting-get-the-sits/"
    },
    {
      "title": "Travel Made Easy: How to See the World on a Budget",
      "url": "https://www.udemy.com/course/travel-made-easy-how-to-see-the-world-on-a-budget/"
    },
    {
      "title": "B1/B2 كيف تحصل على تأشيرة زيارة لأمريكا – دليل المبتدئين",
      "url": "https://www.udemy.com/course/b1b2-usa-visa-guide-arabic/"
    },
    {
      "title": "Digital Nomade le guide complet pour une vie libre",
      "url": "https://www.udemy.com/course/digital-nomade-le-guide/"
    },
    {
      "title": "Bicycle Touring Howto - Biketouring Made Easy for Everyone",
      "url": "https://www.udemy.com/course/bicycle-touring-howto-biketouring-made-easy-for-everyone/"
    },
    {
      "title": "Travel Hacking: How I Travel Twice As Far For Nearly Nothing",
      "url": "https://www.udemy.com/course/travel-hacking-course/"
    },
    {
      "title": "SECRETOS Para Viajar Barato 'ARMANDO' Boletos de Avión...",
      "url": "https://www.udemy.com/course/secretos-de-boletos-de-avion/"
    },
    {
      "title": "Travel! The Ultimate Crash Course to Living on the Road",
      "url": "https://www.udemy.com/course/cheaprvliving/"
    },
    {
      "title": "Accessibility for Individuals in Wheelchairs within Aviation",
      "url": "https://www.udemy.com/course/accessibility-for-individuals-in-wheelchairs-within-aviation/"
    },
    {
      "title": "You don't have to be rich to travel, but you have to start!",
      "url": "https://www.udemy.com/course/start-to-travel-now/"
    },
    {
      "title": "Trabalho Voluntário Cristão na Inglaterra - Tudo Incluso!",
      "url": "https://www.udemy.com/course/trabalho-voluntario-cristao-na-inglaterra/"
    },
    {
      "title": "How to Create Tours/Experiences Using AI",
      "url": "https://www.udemy.com/course/how-to-create-toursexperiences-using-ai/"
    },
    {
      "title": "Thailand Expat Masterclass",
      "url": "https://www.udemy.com/course/thailand-expat-masterclass/"
    },
    {
      "title": "Traveling With Your iPhone",
      "url": "https://www.udemy.com/course/traveling-with-your-iphone/"
    },
    {
      "title": "Canadian Citizenship Test Questions",
      "url": "https://www.udemy.com/course/canadian-citizenship-test-questions/"
    },
    {
      "title": "Viajar a la Amazonía peruana",
      "url": "https://www.udemy.com/course/como-viajar-a-la-amazonia-peruana/"
    },
    {
      "title": "Travel on a Budget:",
      "url": "https://www.udemy.com/course/travel-profit-hacks-save/"
    },
    {
      "title": "ENGLISH ON THE GO: CONVERSATIONAL SKILLS FOR TRAVELERS",
      "url": "https://www.udemy.com/course/english-on-the-go-conversational-skills-for-travelers/"
    },
    {
      "title": "The Ultimate Free Accommodation Guide - Travel for Free",
      "url": "https://www.udemy.com/course/freeaccommodation/"
    },
    {
      "title": "Navigating Canada’s Temporary Resident Visa Program",
      "url": "https://www.udemy.com/course/navigating-canadas-temporary-resident-visa-program-with-borderlaw/"
    },
    {
      "title": "How to Become a Successful Digital Nomad: The Complete Guide",
      "url": "https://www.udemy.com/course/become-a-successful-digital-nomad-the-complete-guide/"
    },
    {
      "title": "Digital Nomad the complete course for freedom life",
      "url": "https://www.udemy.com/course/digital-nomad-the-guide/"
    },
    {
      "title": "Wilderness Survival & Backpacking For Adventures",
      "url": "https://www.udemy.com/course/thebackpackingcourse/"
    },
    {
      "title": "Travelling and Travel Tips",
      "url": "https://www.udemy.com/course/travelling-tips/"
    },
    {
      "title": "Historical sites in Egypt",
      "url": "https://www.udemy.com/course/historical-sites-in-egyptimprove-your-english/"
    },
    {
      "title": "Digital Nomad Travel: Moving to Colombia Long Term",
      "url": "https://www.udemy.com/course/digital-nomad-travel-colombia/"
    },
    {
      "title": "Cruise Staff Course, become an entertainer on board a Cruise",
      "url": "https://www.udemy.com/course/cruise-staff-course-become-an-entertainer-on-board-a-cruise/"
    },
    {
      "title": "كورس البحث عن العمل في الامارات",
      "url": "https://www.udemy.com/course/omarfouda/"
    },
    {
      "title": "How to Complete Canada's Temporary Resident Visa Form",
      "url": "https://www.udemy.com/course/how-to-complete-canadas-temporary-resident-visa-form/"
    },
    {
      "title": "Your Camino Adventure",
      "url": "https://www.udemy.com/course/your-camino-adventure/"
    },
    {
      "title": "Basic Compass Navigation",
      "url": "https://www.udemy.com/course/basic-compass-navigation/"
    },
    {
      "title": "Camino de Santiago 2025 - Everything important about the Way",
      "url": "https://www.udemy.com/course/everything-about-the-camino-de-santiago-in-1-hour-or-less/"
    },
    {
      "title": "Ultimate Northern Lights Course for Beginners",
      "url": "https://www.udemy.com/course/ultimate-northern-lights-course/"
    },
    {
      "title": "旅しながら暮らすためのお金シェア会",
      "url": "https://www.udemy.com/course/travel_and_money/"
    },
    {
      "title": "Worldschooling: A Comprehensive Guide to Long-Term Travel",
      "url": "https://www.udemy.com/course/worldschooling-a-comprehensive-guide-to-long-term-travel/"
    },
    {
      "title": "Ultimate Bucket List, Part II, Travel Tribe",
      "url": "https://www.udemy.com/course/ultimate-bucket-list-2/"
    },
    {
      "title": "Plan Your Morocco Trip : 2025 Morocco Travel Guide",
      "url": "https://www.udemy.com/course/plan-your-morocco-trip-travel-to-morocco-guide-2025/"
    },
    {
      "title": "Before You Go Overseas",
      "url": "https://www.udemy.com/course/before-you-go-overseas/"
    },
    {
      "title": "Língua sueca \"do zero\" (em portugués)",
      "url": "https://www.udemy.com/course/lingua-sueca-do-zero/"
    },
    {
      "title": "iMovie- Complete Video Editing Course: Beginner to Pro 2025",
      "url": "https://www.udemy.com/course/imovie-video-editing/"
    },
    {
      "title": "O Guia Completo De Como Se Mudar E Viver No Exterior",
      "url": "https://www.udemy.com/course/o-guia-completo-de-como-se-mudar-e-viver-no-exterior/"
    },
    {
      "title": "How to Backpack Europe on a Budget",
      "url": "https://www.udemy.com/course/how-to-backpack-europe-on-a-budget/"
    },
    {
      "title": "AirBnb : AirBnb Hacks for Maximizing Profits for Your Pad",
      "url": "https://www.udemy.com/course/make-money-with-airbnb/"
    },
    {
      "title": "【海外移住のリアル】30代フリーランスのためのオランダ移住 25のコツ",
      "url": "https://www.udemy.com/course/moved-to-the-netherlands/"
    },
    {
      "title": "Travel Planning - How To Plan Unique Trips For Yourself",
      "url": "https://www.udemy.com/course/travel-planning/"
    },
    {
      "title": "A course in how to travel the world on a tight budget",
      "url": "https://www.udemy.com/course/a-course-in-how-to-travel-the-world-on-a-tight-budget/"
    },
    {
      "title": "Pengenalan Wisata Kuliner",
      "url": "https://www.udemy.com/course/culinary-tourism/"
    },
    {
      "title": "Khóa học tiếng Trung du lịch",
      "url": "https://www.udemy.com/course/khoa-hoc-tieng-trung-du-lich/"
    },
    {
      "title": "Intro To Van Life: Campervan starter guide",
      "url": "https://www.udemy.com/course/introtovanlife/"
    },
    {
      "title": "Viaggio nella Londra vittoriana",
      "url": "https://www.udemy.com/course/viaggio-nella-londra-vittoriana/"
    },
    {
      "title": "Travel Tips: Travel Free without ruining yourself",
      "url": "https://www.udemy.com/course/travel-tips-travel-free-without-ruining-yourself/"
    },
    {
      "title": "Certified Travel Documentation Specialist",
      "url": "https://www.udemy.com/course/certified-travel-documentation-specialist/"
    },
    {
      "title": "Berlin Relocation Guide",
      "url": "https://www.udemy.com/course/berlin-relocation-guide/"
    },
    {
      "title": "סלובניה + וונציה קיץ 2019",
      "url": "https://www.udemy.com/course/slovenia/"
    },
    {
      "title": "Gardaland Tips & Tricks",
      "url": "https://www.udemy.com/course/gardaland-tips-tricks/"
    },
    {
      "title": "Guía práctica de Portugués para turistas en Brasil",
      "url": "https://www.udemy.com/course/guia-practica-de-portugues-para-turistas-en-brasil/"
    },
    {
      "title": "Relocate to Germany in 2025: A Step-by-Step Visa Guide",
      "url": "https://www.udemy.com/course/relocate-to-germany-in-2025-a-step-by-step-visa-guide/"
    },
    {
      "title": "Study Away 101: Ultimate Guide to Studying Abroad or Away",
      "url": "https://www.udemy.com/course/study-away-101/"
    },
    {
      "title": "Die besten Reisehacks für Weltenbummler & Globetrotter",
      "url": "https://www.udemy.com/course/die-besten-reisehacks-fuer-weltenbummler-globetrotter/"
    },
    {
      "title": "Au Pair 101",
      "url": "https://www.udemy.com/course/au-pair-101/"
    },
    {
      "title": "Voyager Facilement : Budget, Sécurité, Visa et Travail",
      "url": "https://www.udemy.com/course/voyager-facilement-budget-securite-visa-et-travail/"
    },
    {
      "title": "Como comprar passagens aéreas baratas",
      "url": "https://www.udemy.com/course/passagem-descomplicada/"
    },
    {
      "title": "Digital Nomad Masterclass: For Creative Freelancers",
      "url": "https://www.udemy.com/course/how-to-ditch-the-office-and-become-a-digital-nomad/"
    },
    {
      "title": "Master Travel Writing, blogging, travel journalism & Earning",
      "url": "https://www.udemy.com/course/master-travel-writing-blogging-travel-journalism-earning/"
    },
    {
      "title": "How to Become a Successful Digital Nomad in 2025",
      "url": "https://www.udemy.com/course/how-to-become-a-successful-digital-nomad-in-2023-2024/"
    },
    {
      "title": "Haggling 101: How to Negotiate while Traveling | Travel Tips",
      "url": "https://www.udemy.com/course/haggling-101-haggle-like-a-lady-boss/"
    },
    {
      "title": "Digital Nomad: How to be an entrepreneur anywhere on earth",
      "url": "https://www.udemy.com/course/digital-nomad/"
    },
    {
      "title": "Take your Hypnotic Holiday and travel to any destination",
      "url": "https://www.udemy.com/course/hypnotic-holiday/"
    },
    {
      "title": "Scandinavia & N. Europe, Ultimate Bucket List, Travel Tribe",
      "url": "https://www.udemy.com/course/ublscandinavia/"
    },
    {
      "title": "Travel Writer 101",
      "url": "https://www.udemy.com/course/travelwriter101/"
    },
    {
      "title": "Beat the Inflation and Live Well in 2023",
      "url": "https://www.udemy.com/course/fight-the-world-crisis-living-well-in-2023/"
    },
    {
      "title": "How To Backpack",
      "url": "https://www.udemy.com/course/how-to-backpack/"
    },
    {
      "title": "5 Tourism Courses in one.A complete analysis of the industry",
      "url": "https://www.udemy.com/course/5-tourism-courses-in-onea-complete-analysis-of-the-industry/"
    },
    {
      "title": "How To Plan A USA Cross Country Trip",
      "url": "https://www.udemy.com/course/how-to-plan-a-usa-cross-country-trip/"
    },
    {
      "title": "Immigrate to the USA: O-1 and O-2 Visas: Comprehensive Guide",
      "url": "https://www.udemy.com/course/immigrate-to-the-usa-o-1-and-o-2-visas-comprehensive-guide/"
    },
    {
      "title": "21 Day English Guide for Tourists Visiting America",
      "url": "https://www.udemy.com/course/21-day-english-guide-for-tourists-visiting-america/"
    },
    {
      "title": "Leave the Rat Race, Sail the World, and Fund your Adventure",
      "url": "https://www.udemy.com/course/how-to-leave-the-rat-race-sail-the-world-and-make-money/"
    },
    {
      "title": "How To Travel Around Tanzania East Africa On A Budget",
      "url": "https://www.udemy.com/course/how-to-travel-around-tanzania-east-africa-on-a-budget/"
    },
    {
      "title": "Moving to Ireland (What you Need to Know",
      "url": "https://www.udemy.com/course/moving-to-ireland/"
    },
    {
      "title": "Newbie World Traveler",
      "url": "https://www.udemy.com/course/newbie-world-traveler/"
    },
    {
      "title": "Transform Your Future: The Ultimate Tourism Course.",
      "url": "https://www.udemy.com/course/start-your-own-tourism-business/"
    },
    {
      "title": "Predpriprava na delo v tujini",
      "url": "https://www.udemy.com/course/predpriprava-na-delo-v-tujini/"
    },
    {
      "title": "How to Get a U.S. Tourist or Business Visa (B1/B2) + ESTA",
      "url": "https://www.udemy.com/course/how-to-get-a-us-tourist-or-business-visa-b1b2-esta/"
    },
    {
      "title": "Intercâmbio e Voluntariado: Descubra o Mundo Gastando Pouco",
      "url": "https://www.udemy.com/course/curso-decido-viajar-sempre/"
    },
    {
      "title": "How to Travel Around The World with Low Budget",
      "url": "https://www.udemy.com/course/how-to-travel-around-the-world-with-low-budget/"
    },
    {
      "title": "Comment Faire Le Tour Du Monde (Sans Mentir)",
      "url": "https://www.udemy.com/course/comment-faire-le-tour-du-monde-sans-mentir/"
    },
    {
      "title": "The Psychology of Tourism. Understanding Tourist Behaviour.",
      "url": "https://www.udemy.com/course/the-psychology-of-tourism-understanding-tourist-behaviour/"
    },
    {
      "title": "How to Travel around the World with Indian Passport",
      "url": "https://www.udemy.com/course/how-to-travel-around-the-world-with-indian-passport/"
    },
    {
      "title": "Solo Travel Mastery: Travel The World Cheaply & Confidently",
      "url": "https://www.udemy.com/course/travel-hack-mastery-travel-cheaply-smoothly-confidently/"
    },
    {
      "title": "UK Driving Theory Test: Learn How To Pass Your Theory Test",
      "url": "https://www.udemy.com/course/uk-driving-theory-test-learn-how-to-pass-your-theory-test/"
    },
    {
      "title": "Profit from Your Passions: Master Travel Writing & Earn Big",
      "url": "https://www.udemy.com/course/travel-writing-blogging-journaling-publishing/"
    },
    {
      "title": "How to work and live onboard a cruise ship",
      "url": "https://www.udemy.com/course/how-to-work-and-live-onboard-a-cruise-ship/"
    },
    {
      "title": "CLASSE ÉCONOMIQUE - Apprenez à voyager moins cher !",
      "url": "https://www.udemy.com/course/classe-economique-apprenez-a-voyager-moins-cher/"
    },
    {
      "title": "Ecoturismo y Vida en la naturaleza",
      "url": "https://www.udemy.com/course/vida-en-la-naturaleza/"
    },
    {
      "title": "Fulltime RV Travel",
      "url": "https://www.udemy.com/course/fulltime-rv-travel/"
    },
    {
      "title": "Become A Dubai Travel Expert : Earn Or Save on Dubai Tours",
      "url": "https://www.udemy.com/course/become-a-dubai-travel-expert-earn-or-save-on-dubai-tours/"
    },
    {
      "title": "Your Guide To An Amazing Vacation In New York",
      "url": "https://www.udemy.com/course/new-york-city-travel-guide/"
    },
    {
      "title": "Avi Travelz",
      "url": "https://www.udemy.com/course/avi-travelz/"
    },
    {
      "title": "Milhas, Cashback e Programas de Fidelidade - Máscara Bronze",
      "url": "https://www.udemy.com/course/milhas-cashback-e-programas-de-fidelidade-mascara-bronze/"
    },
    {
      "title": "Travel Journaling: How to Write Extraordinary Travel Diaries",
      "url": "https://www.udemy.com/course/travel-journaling/"
    },
    {
      "title": "Cancel Your Mexico Timeshare: The Proven DIY Guide - Insider",
      "url": "https://www.udemy.com/course/the-mexico-timeshare-cancellation-package-new-2023/"
    },
    {
      "title": "Guia completo para tornar-se um Nômade Digital",
      "url": "https://www.udemy.com/course/nomade-digital/"
    },
    {
      "title": "Course about Latvia: Learn basics about country and culture",
      "url": "https://www.udemy.com/course/course-about-latvia-learn-basics-about-country-and-culture/"
    },
    {
      "title": "Trabajar y vivir a bordo de un crucero",
      "url": "https://www.udemy.com/course/trabajar-y-vivir-a-bordo-de-un-crucero/"
    },
    {
      "title": "Save on travel! Be a Self Travel Agent.",
      "url": "https://www.udemy.com/course/be-a-self-travel-agent/"
    },
    {
      "title": "Colombia 101: Your Ultimate Guide to Travel and Living",
      "url": "https://www.udemy.com/course/ready-to-travel-to-colombia-heres-what-you-need-to-know/"
    },
    {
      "title": "How to get Paid to Travel The World",
      "url": "https://www.udemy.com/course/paid-to-travel-the-world/"
    },
    {
      "title": "The Creative Travel Method:",
      "url": "https://www.udemy.com/course/the-creative-travel-method/"
    },
    {
      "title": "Visiting Iran - a small travel guide",
      "url": "https://www.udemy.com/course/free-travel-guide-to-iran/"
    },
    {
      "title": "Avoid US Visa Rejection -Student Visa Interview Guide",
      "url": "https://www.udemy.com/course/avoid-us-visa-rejection-student-visa-interview-guide/"
    }
  ]
}